{
  "slug": "颱風",
  "category": "nature",
  "url": "taiwan.md/nature/颱風",
  "heroImage": "public/article-images/nature/morakot-modis-satellite-2009.webp",
  "_note": "SPORE-IG-PIPELINE v0.4 — accent2 分類色拿掉（哲宇 directive 2026-06-03），全 deck 統一 TWMD 識別色。事實 100% 繼承 knowledge/Nature/颱風.md。",
  "slides": [
    {
      "type": "cover",
      "kicker": "氣候與災害",
      "title": "能預測風雨，\n預測不了命運",
      "subtitle": "台灣與颱風的四百年 — 一場接不住的清晨",
      "hero": true
    },
    {
      "type": "stat",
      "value": "172→57",
      "unit": "公里",
      "label": "從 2000 年的 172 公里，到 2025 年的 57 公里 — 這 25 年，台灣的氣象署、追風團隊、福衛七號、AI 模型一起把颱風 24 小時路徑預報的誤差壓掉了三分之二。但精準度的代價，有時候是來不及。"
    },
    {
      "type": "section",
      "idx": "01",
      "kw": "衝進颱風中心，\n把資料<em>帶回來</em>",
      "body": "2003 年 9 月 1 日杜鵑颱風，台大吳俊傑教授帶著改裝的 ASTRA 噴射機真的衝進颱風中心，丟下探空儀。這是亞洲第一個颱風飛機觀測計畫，截至 2012 年完成 49 個颱風、64 航次任務、投擲 1,051 枚探空儀。第一手大氣資料，讓 24-72 小時路徑預報誤差砍掉 20%。"
    },
    {
      "type": "section",
      "idx": "02",
      "kw": "從太空看雲，\n四分鐘鋪<em>三十天預警</em>",
      "body": "2019 年 6 月發射的福爾摩沙衛星七號，六顆小衛星跟美國 NOAA 合作，每天從軌道丟下 4,000-5,000 筆大氣資料 — 是舊系統 FS3/COSMIC 的兩倍。氣象署六組 AI 整合美國、台灣、日本資料 18 條路徑預測，4 分鐘鋪好 30 天預警地圖 — 比傳統方法快 900 倍。"
    },
    {
      "type": "figure",
      "pull": "2009 莫拉克",
      "image": "public/article-images/nature/morakot-minxiong-flood-2009.webp",
      "caption": "嘉義民雄一處村落在連日豪雨後淹水。Photo: zilupe, CC BY 2.0",
      "body": "莫拉克在阿里山倒下 3,000 毫米雨，是史上最強颱賀伯的 1.5 倍 — 相當於台北全年降雨量在三天內傾倒。中研院後來算出：其中 6.5%，是氣候變遷把雨量放大的結果。"
    },
    {
      "type": "section",
      "idx": "03",
      "kw": "<em>2009 那個清晨</em>，\n獻肚山崩了下來",
      "body": "2009 年 8 月 8 日清晨，71 歲的羅潘春美站在二樓陽台 — 前一天還好好的獻肚山，在連續三天豪雨的侵蝕下崩落。土石像一條黃色的巨龍從山頂衝下來，吞沒街道、房屋、她生活了一輩子的部落。462 位親人，從此消失在群山之間。"
    },
    {
      "type": "quote",
      "text": "再精準的預報，\n都接不住那一秒。"
    },
    {
      "type": "section",
      "idx": "04",
      "kw": "真正接住他們的，\n是一條<em>混濁的溪</em>",
      "body": "同一年，台東 Kakanami 部落的長輩看見溪水變濁、聞到泥土腥味 — 那是上游山體鬆動的徵兆，部落千年口傳的山崩警訊。在沒有衛星、沒有 AI 的山林裡，這條混濁的溪就是他們的雷達。他們即時組織撤離，全村活了下來。"
    },
    {
      "type": "section",
      "idx": "05",
      "kw": "而且，<em>颱風正在改寫</em>，\n而我們還沒準備好",
      "body": "中央研究院推估到本世紀末（2080-2099），台灣每年只剩 1-2 顆颱風 — 但 4 級以上強颱比例增加 150%、降雨強度增加 40%、登陸風速增加 10%。「少而強」的新常態翻轉了過去的防災邏輯：再精準的預報，未必接得住下一個莫拉克。"
    },
    {
      "type": "source",
      "sources": [
        "中央社",
        "國家太空中心 TASA",
        "原住民族電視台",
        "交通部中央氣象署 / 中研院環境變遷研究中心"
      ],
      "url": "taiwan.md/nature/颱風",
      "cta": "覺得值得記住 → 收藏這篇\n想讓更多人看見 → 分享給朋友\n追蹤 Taiwan.md — 台灣人自己寫的台灣"
    }
  ]
}
