{
  "generated_at": "2026-06-17T15:09:50.959Z",
  "status": "ok",
  "summary": {
    "latest_build_seconds": 148,
    "avg_build_seconds_7d": 148,
    "avg_build_seconds_30d": 148,
    "current_page_count": 7553,
    "coverage_days": 1.1,
    "ms_per_page_latest": 20,
    "flag_slow": false
  },
  "trend": [
    {
      "run_id": 27694845309,
      "started_at": "2026-06-17T14:05:10Z",
      "build_seconds": 148,
      "url": "https://github.com/frank890417/taiwan-md/actions/runs/27694845309/job/81915158463"
    },
    {
      "run_id": 27687699481,
      "started_at": "2026-06-17T12:06:45Z",
      "build_seconds": 148,
      "url": "https://github.com/frank890417/taiwan-md/actions/runs/27687699481/job/81890422681"
    },
    {
      "run_id": 27658129631,
      "started_at": "2026-06-17T00:49:02Z",
      "build_seconds": 150,
      "url": "https://github.com/frank890417/taiwan-md/actions/runs/27658129631/job/81796629903"
    },
    {
      "run_id": 27654183692,
      "started_at": "2026-06-16T23:09:54Z",
      "build_seconds": 148,
      "url": "https://github.com/frank890417/taiwan-md/actions/runs/27654183692/job/81784818741"
    },
    {
      "run_id": 27653384139,
      "started_at": "2026-06-16T22:52:11Z",
      "build_seconds": 151,
      "url": "https://github.com/frank890417/taiwan-md/actions/runs/27653384139/job/81782360566"
    },
    {
      "run_id": 27651591254,
      "started_at": "2026-06-16T22:13:14Z",
      "build_seconds": 146,
      "url": "https://github.com/frank890417/taiwan-md/actions/runs/27651591254/job/81776664570"
    },
    {
      "run_id": 27648908902,
      "started_at": "2026-06-16T21:20:20Z",
      "build_seconds": 144,
      "url": "https://github.com/frank890417/taiwan-md/actions/runs/27648908902/job/81767805153"
    },
    {
      "run_id": 27640596036,
      "started_at": "2026-06-16T18:53:32Z",
      "build_seconds": 151,
      "url": "https://github.com/frank890417/taiwan-md/actions/runs/27640596036/job/81739345838"
    },
    {
      "run_id": 27634103259,
      "started_at": "2026-06-16T16:56:26Z",
      "build_seconds": 150,
      "url": "https://github.com/frank890417/taiwan-md/actions/runs/27634103259/job/81716600729"
    },
    {
      "run_id": 27627687209,
      "started_at": "2026-06-16T15:12:22Z",
      "build_seconds": 146,
      "url": "https://github.com/frank890417/taiwan-md/actions/runs/27627687209/job/81693827117"
    },
    {
      "run_id": 27623694090,
      "started_at": "2026-06-16T14:11:14Z",
      "build_seconds": 149,
      "url": "https://github.com/frank890417/taiwan-md/actions/runs/27623694090/job/81679420856"
    },
    {
      "run_id": 27621880983,
      "started_at": "2026-06-16T13:42:21Z",
      "build_seconds": 146,
      "url": "https://github.com/frank890417/taiwan-md/actions/runs/27621880983/job/81672760953"
    },
    {
      "run_id": 27620462304,
      "started_at": "2026-06-16T13:19:31Z",
      "build_seconds": 143,
      "url": "https://github.com/frank890417/taiwan-md/actions/runs/27620462304/job/81667677288"
    },
    {
      "run_id": 27619761982,
      "started_at": "2026-06-16T13:07:43Z",
      "build_seconds": 161,
      "url": "https://github.com/frank890417/taiwan-md/actions/runs/27619761982/job/81665057730"
    },
    {
      "run_id": 27619077004,
      "started_at": "2026-06-16T12:55:58Z",
      "build_seconds": 143,
      "url": "https://github.com/frank890417/taiwan-md/actions/runs/27619077004/job/81662624150"
    }
  ]
}
