{
  "lastUpdated": "2026-05-28T22:53:17.434291Z",
  "schemaVersion": "1.1",
  "totals": {
    "count": 103,
    "platforms": {
      "x": 45,
      "threads": 54,
      "other": 4
    },
    "languages": {
      "zh": 96,
      "en": 7
    },
    "templates": {
      "B": 31,
      "A2": 36,
      "other": 4,
      "A": 28,
      "D": 4
    }
  },
  "recent": [
    {
      "n": 104,
      "date": "2026-05-28",
      "platform": "x",
      "article": "周蕙",
      "articleSlug": "周蕙",
      "category": "music",
      "template": "B 身份反差 hook（KTV 點唱率 25 年 vs 歌手本人 25 年才被認出 → 2026 小巨蛋「練習 26 年」+ 聲帶萎縮 endpoint）",
      "url": "https://x.com/taiwandotmd/status/2060010924015321462",
      "highlight": "哲宇 manual delete 原 X #104 + Threads #103 完成後重發 v2 blueprint copy。**Voice prefix correction**: 「你知道嗎？🎤」字面 prefix 字面 emoji 直接出現於第一行（plugin Rule #14 v2 HARD post-ship verify PASS）。**Repost SOP discovery**: Chrome MCP `type`/JS `execCommand insertText` 在 X ProseMirror 對 `\\n\\n` 段落分隔不 work（會 collapse 成單塊 prose + URL auto-link 重複觸發）→ 改 JXA NSPasteboard `setStringForType \"public.utf8-plain-text\"` 寫 UTF-8 到 clipboard + Cmd+V，X paste handler 正確轉 `\\n\\n` 成 ProseMirror 段落 block 帶 visual blank line spacing。pbcopy 不能用（Mac Chinese locale 強制 Big5 轉碼 UTF-8 中文壞）。Post-ship 5/5 PASS: textHasHook 你知道嗎 ✅ / quote 練習 26 年 ✅ / quote 最後一次唱歌 ✅ / close 她叫周蕙 ✅ / t.co shortener ✅。<br><br>🚨 **PREVIOUS RETRACTED 2026-05-28 18:00 per 哲宇 directive「周蕙 → 刪掉重發」** — voice drift case: 第一行「走進台灣任何一間 KTV」**完全無「你知道嗎？」prefix**，是觸發 plugin Rule #14 v2 HARD gate 升級的三條 spore 之一。哲宇 callout 後修補 plugin 升 HARD + 落實 STRICT SPORE-WRITING READ GATE in routine skill v3.1。重發等 article R2 EVOLVE ship 後（已 `f32895640` ship）+ 新 blueprint 寫到 docs/factory/spore-blueprints/ + plugin Rule #14 v2 PASS。原 retracted URL: ~~`https://x.com/taiwandotmd/status/2059934783946523132`~~ — **同 #103 內容 X 單則 inline UTM URL 版**（X Premium 25K char 無壓）。Tier 1a 具體性槓桿 + 三層反差（KTV 人人聽過 vs 歌手沒人認得 / 1999 漫畫娃娃藏臉 vs 2026 小巨蛋首攻 / 練習 26 年 vs 聲帶萎縮）。**routine twmd-spore-publish-daily 2026-05-28 17:38 ship**（08:11 spore-pick-daily 第六轉 cycle 後本日第二棒）。Quality gate 全 PASS：prose-health score=1 ≤ 3 / word-count 周蕙 article ≥ 4500 CJK / footnote-density A / media-richness 3 image ≥ 2 hard / lastVerified 2026-05-19 9 days ≤ 90。X inline UTM URL 版（utm_campaign=s104）t.co auto-shortener。Routine context auto-decisions v3.8：Platform both / Tier 1a default / single version / zh only / 0 observer gate / Image plugin check / CI/CD wait gate auto-PASS（HTTP 200 + 練習 26 年 + 聲帶萎縮 + 蕙兒 9× keyword hits）。配圖 1080×1080 square 496KB via make-spore.sh --prod。Chrome MCP osascript clipboard PNGf + navigate x.com/compose/post + click textbox + cmd+v image + click textbox + type 單塊 prose + inline UTM URL → JS click tweetButton. post-ship verify 5/5 PASS: textHasHook KTV ✅ / textHasQuote 練習 26 年 ✅ / textHasQuote 鋸子 ✅ / textHasCloseLine 同一首歌 ✅ / hasShortener t.co ✅。**Stage 1 SELECT defer 鏈**：5/28 P0 二二八 高敏感 routine defer HTML comment（5/27 cycle 已加）+ P2 曾博恩 5/21 中-高敏感（政治脫口秀+鄭南榕梗+娛樂稅）routine spirit defer HTML comment 新加 + P2 施振榮 5/21 word-count 2368 < 4500 fail skip + P3 林央敏 5/23 article 不存在 skip → FIFO P2 周蕙 5/24（score=45 5/19 ship 趁熱窗口 +1 day）first to pass all 5 hard gates。Pitfall 6 max 1 retry hard rule 觀察：本次 ship 0 retry / before=4 post-click modal close clean / no duplicate ship. Blueprint: 本 spore 無預先 blueprint，body inline。",
      "views_7d": null,
      "views_latest": null,
      "engagements_7d": null,
      "rate_7d": null,
      "backfilled": false
    },
    {
      "n": 103,
      "date": "2026-05-28",
      "platform": "threads",
      "article": "周蕙",
      "articleSlug": "周蕙",
      "category": "music",
      "template": "B 身份反差 hook（KTV 點唱率 25 年 vs 歌手本人 25 年才被認出 → 2026 小巨蛋「練習 26 年」+ 聲帶萎縮 endpoint）",
      "url": "https://www.threads.com/@taiwandotmd/post/DY4u5UzAVcT",
      "highlight": "哲宇 manual delete 完成後重發 v2 blueprint copy。**結構**：主貼 374 CJK chars (under Threads 500 limit) 含 1080×1080 square 配圖 + Self-reply 「完整故事 👉」+ UTM URL（utm_campaign=s103, replyLen 105）+ Threads OG card auto-preview 周蕙 article。Voice prefix「你知道嗎？🎤」字面 emoji 第一行（plugin Rule #14 v2 HARD post-ship verify PASS via og:description 抓到完整 7 paragraph \\n\\n 結構）。**Repost SOP discovery**: JXA NSPasteboard UTF-8 + Cmd+V 是 multi-paragraph 中文 spore 唯一 reliable path（pbcopy 在 Mac Chinese locale 強制 Big5 轉碼壞 UTF-8 中文；execCommand insertText 不分段；computer.type 吞 ASCII 數字+空格）。Pre-ship 11/11 PASS / post-ship og:description 4/4 PASS (hookPresent + emojiPresent + quote 練習 26 年 + close 她叫周蕙)。<br><br>🚨 **PREVIOUS RETRACTED 2026-05-28 18:00 per 哲宇 directive「周蕙 → 刪掉重發」** — voice drift case，同 #104。重發等 article R2 EVOLVE ship 後（已 `f32895640` ship）+ 新 blueprint 寫到 docs/factory/spore-blueprints/ + plugin Rule #14 v2 PASS。原 retracted URL: ~~`https://www.threads.com/@taiwandotmd/post/DY4LbtKgbn6`~~ — **routine twmd-spore-publish-daily 2026-05-28 17:38 自動 ship**。Tier 1a 具體性槓桿（1999-08-26 福茂《周蕙精選》+ 蕙兒漫畫娃娃 + 22 歲不對外露面 + 王菲 1997 粵語版 + 姚若龍/陳小霞 + 25 年 KTV 點唱榜 + 2026-04-25 小巨蛋 + 49 歲 + 「練習 26 年」原話 + 「鋸子」聲帶萎縮 + 「不曉得這會不會是最後一次」原話 + 〈約定〉首末呼應 closure 11 個 anchor + 三層反差 hook）。**結構**：主貼 421 chars (~320 CJK + 全形/標點) 含配圖 + Self-reply 「完整故事 👉」 + UTM URL（utm_campaign=s103, replyLen=105）+ Threads OG card auto-preview。三板斧 不是 0 / —— 0 / 不僅 0 ✅✅✅。事實查核閘全 ✅（11 anchor 全 article footnote verbatim 對齊：[^1] 漫畫娃娃 / [^2] 25 萬張 / [^5] 練習 26 年 + 鋸子 + 最後一次原話 / [^9] 福茂 1999-08-26 + 先聲奪人 / [^12-13] 王菲 1997 + 姚若龍/陳小霞 / [^34] 小巨蛋 / article line 41 + 77 + 152 + 158 + 164-170 cross-validate）。**Stage 1 SELECT defer 鏈** 同 #104。配圖：[`public/spore-images/周蕙-square.png`](../../public/spore-images/周蕙-square.png) 1080×1080 496KB via make-spore.sh --prod (9d 舊文章 prod live)。Pitfall 6 instrumentation 觀察：5/28 12:06 commit `8fc4bf658` SPORE-HARVEST §Chrome MCP Pitfall 6 instrument 後第一次 production cycle，before=4 baseline 抓到，click 發佈 modal close clean 不需 retry — 5/27 #101 落日飛車 3-retry duplicate 教訓本次 0 retry 通過 hard rule。Blueprint: 本 spore 無預先 blueprint，body inline。",
      "views_7d": null,
      "views_latest": null,
      "engagements_7d": null,
      "rate_7d": null,
      "backfilled": false
    },
    {
      "n": 102,
      "date": "2026-05-27",
      "platform": "x",
      "article": "落日飛車",
      "articleSlug": "落日飛車",
      "category": "music",
      "template": "A2 首尾呼應變體（2010 Photo Booth pre-set 起點 → 2023 Coachella 沙漠舞台終點，14 年同一張圖回扣）",
      "url": "https://x.com/taiwandotmd/status/2059577645722210476",
      "highlight": "**同 #101 內容 X 單則 inline UTM URL 版**（X Premium 25K char 無壓，不拆 thread）。Tier 1b 具體性槓桿（2010 / 19 歲 / MySpace / Mac Photo Booth / 雲霄飛車剪影夕陽 五個獨立可查 anchor + 反差 hook 隨手挑 pre-set → Coachella 沙漠舞台背板字）。**routine twmd-spore-publish-daily 17:35 第二次成功 ship**（早上 10:21 #97/#98 美食總覽 後本日第二發）。Quality gate 全 PASS：prose-health score=1 ≤ 3 / word-count 4531 CJK = 101% threshold / footnote-density A (0 violations) / media-richness 3 image ≥ 2 hard / lastVerified 4 days ≤ 90。X inline UTM URL 版（utm_campaign=s102）t.co/XLuIRQBAbc auto-shortener。Routine context auto-decisions v3.8：Platform both 雙發 / Tier 1b default / single version / zh only / 0 observer gate / Image plugin check / CI/CD wait gate auto-PASS（4d 舊文章 prod live HTTP 200 + keywords「Photo Booth」+「Coachella」+「落日飛車」all hits）。配圖 1080×1080 square 535KB via make-spore.sh --prod。Chrome MCP osascript clipboard set PNGf + navigate x.com/home inline composer + cmd+v image + JS execCommand insertText with single literal string (no \\\\n\\\\n breaks — X composer thread-mode auto-split corrupts multi-paragraph insertText causing 6× URL duplication, single-paragraph spaced text works) → JS dispatchEvent click on `[data-testid=\"tweetButtonInline\"]`. post-ship verify 4/4 PASS: textHasHook 你知道嗎 ✅ / textHasPhoto Photo Booth ✅ / textHasCoachella Coachella ✅ / textHasClose 沙漠的舞台 ✅。Blueprint: [SPORE-BLUEPRINTS/101-落日飛車.md](SPORE-BLUEPRINTS/101-落日飛車.md)（X 共用 Threads #101 blueprint）。",
      "views_7d": null,
      "views_latest": null,
      "engagements_7d": null,
      "rate_7d": null,
      "backfilled": false
    },
    {
      "n": 101,
      "date": "2026-05-27",
      "platform": "threads",
      "article": "落日飛車",
      "articleSlug": "落日飛車",
      "category": "music",
      "template": "A2 首尾呼應變體（2010 Photo Booth pre-set 起點 → 2023 Coachella 沙漠舞台終點，14 年同一張圖回扣）",
      "url": "https://www.threads.com/@taiwandotmd/post/DY1oPxokz0L",
      "highlight": "**routine twmd-spore-publish-daily 17:35 自動 ship**（SPORE-INBOX P0 二二八事件 fail 圖片 gate + P2 曾博恩/施振榮/飲料封膜機/尊 fail image gate skip → FIFO P2 落日飛車 5/23 candidate first to pass all 5 hard gates）。Tier 1b 具體性槓桿（2010 / 19 歲 / MySpace / Mac Photo Booth pre-set / 雲霄飛車剪影夕陽 五個獨立可查 anchor + 隨手挑背景圖 vs Coachella 沙漠舞台背板字 反差 hook）。**結構**：主貼 320 CJK 含配圖 + Self-reply 完整故事 👉 UTM URL（utm_campaign=s101）+ Threads OG card auto-preview。三板斧 不是 0 / —— 0 / 不僅 0 ✅✅✅（spore 史上最乾淨自檢結果）。事實查核閘全 ✅（2010 Photo Booth + 1300 度 + 2018 Audiotree first 台灣樂團 + 2023 Coachella 超過二十年來首組 [Blow 街聲] + 「關鍵節點全部是無計算的當下選擇」article §策展人筆記 verbatim — 避坑 33 年 typo per article §爭議觀點）。配圖：[`public/spore-images/落日飛車-square.png`](../../public/spore-images/落日飛車-square.png) 1080×1080 535KB via make-spore.sh --prod (4d 舊文章 prod live)。Blueprint: [SPORE-BLUEPRINTS/101-落日飛車.md](SPORE-BLUEPRINTS/101-落日飛車.md)。**Pipeline 教訓**：Threads contenteditable execCommand insertText with insertLineBreak between paragraphs strips \\\\n (300 CJK 顯示為單塊 prose 但可讀) — 接受作為 routine constraint，未來研究是否用 insertParagraph 保 spacing。X contenteditable 對 multi-paragraph + URL 的 insertText 觸發 thread-mode auto-split + URL 6× duplication — 必須用 single-paragraph spaced text。詳見 §復盤 / LESSONS-INBOX entry。",
      "views_7d": null,
      "views_latest": null,
      "engagements_7d": null,
      "rate_7d": null,
      "backfilled": false
    },
    {
      "n": 100,
      "date": "2026-05-27",
      "platform": "x",
      "article": "portaly-五月公開信",
      "articleSlug": "portaly-五月公開信",
      "category": "meta",
      "template": "F 站方公開信（公開感謝 + 一個月進化 + 跨單位合作 + 透明用途 + 邀請）",
      "url": "https://x.com/taiwandotmd/status/2059525841735016585",
      "highlight": "**同 #99 內容**：X 單則整版 712 CJK 含圖 + URL inline 版本（X Premium 解鎖長文 25K char 無壓）。哲宇 5/27 「x 目前沒有字元限制要記得」directive — 不拆 thread 直接整版。Blueprint 共用 [SPORE-BLUEPRINTS/099-公開信-portaly-五月.md](SPORE-BLUEPRINTS/099-公開信-portaly-五月.md)。",
      "views_7d": null,
      "views_latest": null,
      "engagements_7d": null,
      "rate_7d": null,
      "backfilled": false
    }
  ],
  "topPerformers": [
    {
      "n": 29,
      "article": "🌋 李洋（v2，留言更正）",
      "platform": "threads",
      "views": 300000,
      "viewsSource": "7d",
      "engagements": 27000,
      "rate": 9.0,
      "badge": "🌋 史上最強",
      "date": "2026-04-14"
    },
    {
      "n": 25,
      "article": "張懸與安溥",
      "platform": "threads",
      "views": 190000,
      "viewsSource": "7d",
      "engagements": 2894,
      "rate": 1.52,
      "badge": "🌋 史上最強",
      "date": "2026-04-13"
    },
    {
      "n": 30,
      "article": "李洋（v3 場景修正）",
      "platform": "x",
      "views": 136474,
      "viewsSource": "7d",
      "engagements": 4907,
      "rate": 3.6,
      "badge": "🔥 平台最強",
      "date": "2026-04-14"
    },
    {
      "n": 35,
      "article": "台灣高鐵（v3 事實修正版）",
      "platform": "threads",
      "views": 71000,
      "viewsSource": "7d",
      "engagements": 379,
      "rate": 0.53,
      "badge": "⭐ 高峰",
      "date": "2026-04-19"
    },
    {
      "n": 54,
      "article": "黑冠麻鷺",
      "platform": "x",
      "views": 69664,
      "viewsSource": "7d",
      "engagements": 2009,
      "rate": 2.88,
      "badge": "⭐ 高峰",
      "date": "2026-04-30"
    },
    {
      "n": 45,
      "article": "壞特",
      "platform": "threads",
      "views": 65400,
      "viewsSource": "7d",
      "engagements": 1151,
      "rate": 1.76,
      "badge": "⭐ 高峰",
      "date": "2026-04-26"
    },
    {
      "n": 53,
      "article": "黑冠麻鷺",
      "platform": "threads",
      "views": 65000,
      "viewsSource": "7d",
      "engagements": 321,
      "rate": 0.49,
      "badge": "⭐ 高峰",
      "date": "2026-04-30"
    },
    {
      "n": 36,
      "article": "台灣高鐵（v3 事實修正版）",
      "platform": "x",
      "views": 63868,
      "viewsSource": "7d",
      "engagements": 450,
      "rate": 0.7,
      "badge": "⭐ 高峰",
      "date": "2026-04-19"
    }
  ],
  "amplification": [],
  "platformComparison": {
    "threads": {
      "count": 35,
      "avgViews": 27511,
      "maxViews": 300000,
      "avgRate": 5.94,
      "maxRate": 14.38
    },
    "x": {
      "count": 33,
      "avgViews": 18245,
      "maxViews": 136474,
      "avgRate": 4.02,
      "maxRate": 10.71
    }
  },
  "backfillWarnings": [
    {
      "n": 85,
      "article": "臺灣漫遊錄",
      "platform": "x",
      "publishedDays": 6,
      "status": "waiting",
      "url": "https://x.com/taiwandotmd/status/2058211699229134864"
    },
    {
      "n": 84,
      "article": "臺灣漫遊錄",
      "platform": "threads",
      "publishedDays": 6,
      "status": "waiting",
      "url": "https://www.threads.com/@taiwandotmd/post/DYr71D9k-qA"
    },
    {
      "n": 83,
      "article": "許倬雲",
      "platform": "x",
      "publishedDays": 6,
      "status": "waiting",
      "url": "https://x.com/taiwandotmd/status/2058183941593719181"
    },
    {
      "n": 82,
      "article": "許倬雲",
      "platform": "threads",
      "publishedDays": 6,
      "status": "waiting",
      "url": "https://www.threads.com/@taiwandotmd/post/DYru52Bk31S"
    },
    {
      "n": 81,
      "article": "馬英九",
      "platform": "x",
      "publishedDays": 6,
      "status": "waiting",
      "url": "https://x.com/taiwandotmd/status/2057861183848550878"
    },
    {
      "n": 80,
      "article": "馬英九",
      "platform": "threads",
      "publishedDays": 6,
      "status": "waiting",
      "url": "https://www.threads.com/@taiwandotmd/post/DYpdfODkxQU"
    },
    {
      "n": 86,
      "article": "鄭愁予",
      "platform": "threads",
      "publishedDays": 5,
      "status": "waiting",
      "url": "https://www.threads.com/@taiwandotmd/post/DYt_TMpE2WV"
    },
    {
      "n": 91,
      "article": "江賢二",
      "platform": "threads",
      "publishedDays": 4,
      "status": "waiting",
      "url": "https://www.threads.com/@taiwandotmd/post/DYwhhzFgfe0"
    },
    {
      "n": 90,
      "article": "雷亞遊戲",
      "platform": "x",
      "publishedDays": 4,
      "status": "waiting",
      "url": "https://x.com/taiwandotmd/status/2058811390337622339"
    },
    {
      "n": 89,
      "article": "雷亞遊戲",
      "platform": "threads",
      "publishedDays": 4,
      "status": "waiting",
      "url": "https://www.threads.com/@taiwandotmd/post/DYwMkzBgW8k"
    },
    {
      "n": 88,
      "article": "半導體產業",
      "platform": "x",
      "publishedDays": 4,
      "status": "waiting",
      "url": "https://x.com/taiwandotmd/status/2058735515021783190"
    },
    {
      "n": 87,
      "article": "半導體產業",
      "platform": "threads",
      "publishedDays": 4,
      "status": "waiting",
      "url": "https://www.threads.com/@taiwandotmd/post/DYvqEURgXm-"
    },
    {
      "n": 96,
      "article": "尹衍樑",
      "platform": "x",
      "publishedDays": 3,
      "status": "waiting",
      "url": "https://x.com/taiwandotmd/status/2059290686671982831"
    },
    {
      "n": 95,
      "article": "尹衍樑",
      "platform": "threads",
      "publishedDays": 3,
      "status": "waiting",
      "url": "https://www.threads.com/@taiwandotmd/post/DYzmiFqE0mC"
    },
    {
      "n": 94,
      "article": "大宇雙劍",
      "platform": "x",
      "publishedDays": 3,
      "status": "waiting",
      "url": "https://x.com/taiwandotmd/status/2059239795231281223"
    }
  ],
  "noUrlHistorical": [
    {
      "n": 12,
      "article": "台灣民主轉型",
      "platform": "threads",
      "publishedDays": 52,
      "status": "NO_URL"
    },
    {
      "n": 3,
      "article": "林書豪",
      "platform": "threads",
      "publishedDays": 55,
      "status": "NO_URL"
    },
    {
      "n": 2,
      "article": "齊柏林",
      "platform": "threads",
      "publishedDays": 66,
      "status": "NO_URL"
    },
    {
      "n": 1,
      "article": "數位身分證與個資爭議",
      "platform": "threads",
      "publishedDays": 66,
      "status": "NO_URL"
    }
  ],
  "weeklyPulse": [
    {
      "week": "2026-W15",
      "published": 18,
      "avgViews": 3947
    },
    {
      "week": "2026-W16",
      "published": 13,
      "avgViews": 67044
    },
    {
      "week": "2026-W17",
      "published": 10,
      "avgViews": 18791
    },
    {
      "week": "2026-W18",
      "published": 12,
      "avgViews": 29325
    },
    {
      "week": "2026-W19",
      "published": 13,
      "avgViews": 6328
    },
    {
      "week": "2026-W20",
      "published": 6,
      "avgViews": 15216
    },
    {
      "week": "2026-W21",
      "published": 8,
      "avgViews": 742
    },
    {
      "week": "2026-W22",
      "published": 18,
      "avgViews": 433
    }
  ],
  "harvestStatus": [
    {
      "n": 104,
      "article": "周蕙",
      "platform": "x",
      "publishDate": "2026-05-28",
      "daysSincePublish": 1,
      "withinHarvestWindow": true,
      "harvestCount": 0,
      "lastHarvest": null
    },
    {
      "n": 103,
      "article": "周蕙",
      "platform": "threads",
      "publishDate": "2026-05-28",
      "daysSincePublish": 1,
      "withinHarvestWindow": true,
      "harvestCount": 0,
      "lastHarvest": null
    },
    {
      "n": 102,
      "article": "落日飛車",
      "platform": "x",
      "publishDate": "2026-05-27",
      "daysSincePublish": 2,
      "withinHarvestWindow": true,
      "harvestCount": 0,
      "lastHarvest": null
    },
    {
      "n": 101,
      "article": "落日飛車",
      "platform": "threads",
      "publishDate": "2026-05-27",
      "daysSincePublish": 2,
      "withinHarvestWindow": true,
      "harvestCount": 0,
      "lastHarvest": null
    },
    {
      "n": 100,
      "article": "portaly-五月公開信",
      "platform": "x",
      "publishDate": "2026-05-27",
      "daysSincePublish": 2,
      "withinHarvestWindow": true,
      "harvestCount": 0,
      "lastHarvest": null
    },
    {
      "n": 99,
      "article": "portaly-五月公開信",
      "platform": "threads",
      "publishDate": "2026-05-27",
      "daysSincePublish": 2,
      "withinHarvestWindow": true,
      "harvestCount": 0,
      "lastHarvest": null
    },
    {
      "n": 98,
      "article": "台灣美食總覽",
      "platform": "x",
      "publishDate": "2026-05-27",
      "daysSincePublish": 2,
      "withinHarvestWindow": true,
      "harvestCount": 0,
      "lastHarvest": null
    },
    {
      "n": 97,
      "article": "台灣美食總覽",
      "platform": "threads",
      "publishDate": "2026-05-27",
      "daysSincePublish": 2,
      "withinHarvestWindow": true,
      "harvestCount": 0,
      "lastHarvest": null
    },
    {
      "n": 96,
      "article": "尹衍樑",
      "platform": "x",
      "publishDate": "2026-05-26",
      "daysSincePublish": 3,
      "withinHarvestWindow": true,
      "harvestCount": 3,
      "lastHarvest": "2026-05-29 06:30"
    },
    {
      "n": 95,
      "article": "尹衍樑",
      "platform": "threads",
      "publishDate": "2026-05-26",
      "daysSincePublish": 3,
      "withinHarvestWindow": true,
      "harvestCount": 3,
      "lastHarvest": "2026-05-29 06:30"
    },
    {
      "n": 94,
      "article": "大宇雙劍",
      "platform": "x",
      "publishDate": "2026-05-26",
      "daysSincePublish": 3,
      "withinHarvestWindow": true,
      "harvestCount": 2,
      "lastHarvest": "2026-05-29 06:30"
    },
    {
      "n": 93,
      "article": "國家人權博物館",
      "platform": "threads",
      "publishDate": "2026-05-26",
      "daysSincePublish": 3,
      "withinHarvestWindow": true,
      "harvestCount": 0,
      "lastHarvest": null
    },
    {
      "n": 92,
      "article": "大宇雙劍",
      "platform": "threads",
      "publishDate": "2026-05-26",
      "daysSincePublish": 3,
      "withinHarvestWindow": true,
      "harvestCount": 1,
      "lastHarvest": "2026-05-28 06:30"
    },
    {
      "n": 91,
      "article": "江賢二",
      "platform": "threads",
      "publishDate": "2026-05-25",
      "daysSincePublish": 4,
      "withinHarvestWindow": true,
      "harvestCount": 4,
      "lastHarvest": "2026-05-29 06:30"
    },
    {
      "n": 90,
      "article": "雷亞遊戲",
      "platform": "x",
      "publishDate": "2026-05-25",
      "daysSincePublish": 4,
      "withinHarvestWindow": true,
      "harvestCount": 4,
      "lastHarvest": "2026-05-29 06:30"
    },
    {
      "n": 89,
      "article": "雷亞遊戲",
      "platform": "threads",
      "publishDate": "2026-05-25",
      "daysSincePublish": 4,
      "withinHarvestWindow": true,
      "harvestCount": 4,
      "lastHarvest": "2026-05-29 06:30"
    },
    {
      "n": 88,
      "article": "半導體產業",
      "platform": "x",
      "publishDate": "2026-05-25",
      "daysSincePublish": 4,
      "withinHarvestWindow": true,
      "harvestCount": 4,
      "lastHarvest": "2026-05-29 06:30"
    },
    {
      "n": 87,
      "article": "半導體產業",
      "platform": "threads",
      "publishDate": "2026-05-25",
      "daysSincePublish": 4,
      "withinHarvestWindow": true,
      "harvestCount": 4,
      "lastHarvest": "2026-05-29 06:30"
    },
    {
      "n": 86,
      "article": "鄭愁予",
      "platform": "threads",
      "publishDate": "2026-05-24",
      "daysSincePublish": 5,
      "withinHarvestWindow": true,
      "harvestCount": 5,
      "lastHarvest": "2026-05-29 06:30"
    },
    {
      "n": 85,
      "article": "臺灣漫遊錄",
      "platform": "x",
      "publishDate": "2026-05-23",
      "daysSincePublish": 6,
      "withinHarvestWindow": true,
      "harvestCount": 5,
      "lastHarvest": "2026-05-29 06:30"
    },
    {
      "n": 84,
      "article": "臺灣漫遊錄",
      "platform": "threads",
      "publishDate": "2026-05-23",
      "daysSincePublish": 6,
      "withinHarvestWindow": true,
      "harvestCount": 5,
      "lastHarvest": "2026-05-29 06:30"
    },
    {
      "n": 83,
      "article": "許倬雲",
      "platform": "x",
      "publishDate": "2026-05-23",
      "daysSincePublish": 6,
      "withinHarvestWindow": true,
      "harvestCount": 6,
      "lastHarvest": "2026-05-29 06:30"
    },
    {
      "n": 82,
      "article": "許倬雲",
      "platform": "threads",
      "publishDate": "2026-05-23",
      "daysSincePublish": 6,
      "withinHarvestWindow": true,
      "harvestCount": 6,
      "lastHarvest": "2026-05-29 06:30"
    },
    {
      "n": 81,
      "article": "馬英九",
      "platform": "x",
      "publishDate": "2026-05-23",
      "daysSincePublish": 6,
      "withinHarvestWindow": true,
      "harvestCount": 6,
      "lastHarvest": "2026-05-29 06:30"
    },
    {
      "n": 80,
      "article": "馬英九",
      "platform": "threads",
      "publishDate": "2026-05-23",
      "daysSincePublish": 6,
      "withinHarvestWindow": true,
      "harvestCount": 6,
      "lastHarvest": "2026-05-29 06:30"
    },
    {
      "n": 78,
      "article": "泛科學",
      "platform": "threads",
      "publishDate": "2026-05-20",
      "daysSincePublish": 9,
      "withinHarvestWindow": false,
      "harvestCount": 6,
      "lastHarvest": "2026-05-27 07:00"
    },
    {
      "n": 77,
      "article": "臺灣前途決議文",
      "platform": "x",
      "publishDate": "2026-05-17",
      "daysSincePublish": 12,
      "withinHarvestWindow": false,
      "harvestCount": 6,
      "lastHarvest": "2026-05-24 07:00"
    },
    {
      "n": 76,
      "article": "臺灣前途決議文",
      "platform": "threads",
      "publishDate": "2026-05-17",
      "daysSincePublish": 12,
      "withinHarvestWindow": false,
      "harvestCount": 6,
      "lastHarvest": "2026-05-24 07:00"
    },
    {
      "n": 75,
      "article": "陳建年",
      "platform": "x",
      "publishDate": "2026-05-17",
      "daysSincePublish": 12,
      "withinHarvestWindow": false,
      "harvestCount": 6,
      "lastHarvest": "2026-05-24 07:00"
    },
    {
      "n": 74,
      "article": "陳建年",
      "platform": "threads",
      "publishDate": "2026-05-17",
      "daysSincePublish": 12,
      "withinHarvestWindow": false,
      "harvestCount": 6,
      "lastHarvest": "2026-05-24 07:00"
    },
    {
      "n": 73,
      "article": "蘋果西打",
      "platform": "x",
      "publishDate": "2026-05-12",
      "daysSincePublish": 17,
      "withinHarvestWindow": false,
      "harvestCount": 5,
      "lastHarvest": "2026-05-19 07:00"
    },
    {
      "n": 72,
      "article": "蘋果西打",
      "platform": "threads",
      "publishDate": "2026-05-12",
      "daysSincePublish": 17,
      "withinHarvestWindow": false,
      "harvestCount": 5,
      "lastHarvest": "2026-05-19 07:00"
    },
    {
      "n": 71,
      "article": "台灣無人機產業【未發布】",
      "platform": "x",
      "publishDate": "2026-05-10",
      "daysSincePublish": 19,
      "withinHarvestWindow": false,
      "harvestCount": 6,
      "lastHarvest": "2026-05-19 07:00"
    },
    {
      "n": 70,
      "article": "台灣無人機產業",
      "platform": "threads",
      "publishDate": "2026-05-10",
      "daysSincePublish": 19,
      "withinHarvestWindow": false,
      "harvestCount": 5,
      "lastHarvest": "2026-05-18 07:00"
    },
    {
      "n": 69,
      "article": "台灣企業：台積電",
      "platform": "x",
      "publishDate": "2026-05-09",
      "daysSincePublish": 20,
      "withinHarvestWindow": false,
      "harvestCount": 3,
      "lastHarvest": "2026-05-16 07:00"
    },
    {
      "n": 68,
      "article": "台灣企業：台積電",
      "platform": "threads",
      "publishDate": "2026-05-09",
      "daysSincePublish": 20,
      "withinHarvestWindow": false,
      "harvestCount": 3,
      "lastHarvest": "2026-05-16 07:00"
    },
    {
      "n": 67,
      "article": "聶永真",
      "platform": "x",
      "publishDate": "2026-05-08",
      "daysSincePublish": 21,
      "withinHarvestWindow": false,
      "harvestCount": 5,
      "lastHarvest": "2026-05-16 07:00"
    },
    {
      "n": 66,
      "article": "聶永真",
      "platform": "threads",
      "publishDate": "2026-05-08",
      "daysSincePublish": 21,
      "withinHarvestWindow": false,
      "harvestCount": 5,
      "lastHarvest": "2026-05-16 07:00"
    },
    {
      "n": 65,
      "article": "寶島聯播網訪談（自述版）",
      "platform": "x",
      "publishDate": "2026-05-05",
      "daysSincePublish": 24,
      "withinHarvestWindow": false,
      "harvestCount": 3,
      "lastHarvest": "2026-05-12"
    },
    {
      "n": 64,
      "article": "寶島聯播網訪談",
      "platform": "x",
      "publishDate": "2026-05-05",
      "daysSincePublish": 24,
      "withinHarvestWindow": false,
      "harvestCount": 2,
      "lastHarvest": "2026-05-12"
    },
    {
      "n": 63,
      "article": "寶島聯播網訪談",
      "platform": "threads",
      "publishDate": "2026-05-05",
      "daysSincePublish": 24,
      "withinHarvestWindow": false,
      "harvestCount": 2,
      "lastHarvest": "2026-05-12"
    },
    {
      "n": 62,
      "article": "台灣與史瓦帝尼",
      "platform": "x",
      "publishDate": "2026-05-05",
      "daysSincePublish": 24,
      "withinHarvestWindow": false,
      "harvestCount": 2,
      "lastHarvest": "2026-05-12"
    },
    {
      "n": 61,
      "article": "台灣與史瓦帝尼",
      "platform": "threads",
      "publishDate": "2026-05-05",
      "daysSincePublish": 24,
      "withinHarvestWindow": false,
      "harvestCount": 2,
      "lastHarvest": "2026-05-12"
    },
    {
      "n": 60,
      "article": "黃魚鴞",
      "platform": "x",
      "publishDate": "2026-05-04",
      "daysSincePublish": 25,
      "withinHarvestWindow": false,
      "harvestCount": 3,
      "lastHarvest": "2026-05-12"
    },
    {
      "n": 59,
      "article": "黃魚鴞",
      "platform": "threads",
      "publishDate": "2026-05-04",
      "daysSincePublish": 25,
      "withinHarvestWindow": false,
      "harvestCount": 3,
      "lastHarvest": "2026-05-12"
    },
    {
      "n": 58,
      "article": "賈永婕",
      "platform": "x",
      "publishDate": "2026-05-02",
      "daysSincePublish": 27,
      "withinHarvestWindow": false,
      "harvestCount": 4,
      "lastHarvest": "2026-05-08"
    },
    {
      "n": 57,
      "article": "賈永婕",
      "platform": "threads",
      "publishDate": "2026-05-02",
      "daysSincePublish": 27,
      "withinHarvestWindow": false,
      "harvestCount": 4,
      "lastHarvest": "2026-05-08"
    },
    {
      "n": 56,
      "article": "海底電纜",
      "platform": "x",
      "publishDate": "2026-04-30",
      "daysSincePublish": 29,
      "withinHarvestWindow": false,
      "harvestCount": 2,
      "lastHarvest": "2026-05-08"
    },
    {
      "n": 55,
      "article": "海底電纜",
      "platform": "threads",
      "publishDate": "2026-04-30",
      "daysSincePublish": 29,
      "withinHarvestWindow": false,
      "harvestCount": 2,
      "lastHarvest": "2026-05-08"
    },
    {
      "n": 54,
      "article": "黑冠麻鷺",
      "platform": "x",
      "publishDate": "2026-04-30",
      "daysSincePublish": 29,
      "withinHarvestWindow": false,
      "harvestCount": 2,
      "lastHarvest": "2026-05-08"
    },
    {
      "n": 53,
      "article": "黑冠麻鷺",
      "platform": "threads",
      "publishDate": "2026-04-30",
      "daysSincePublish": 29,
      "withinHarvestWindow": false,
      "harvestCount": 2,
      "lastHarvest": "2026-05-08"
    },
    {
      "n": 52,
      "article": "台灣邦交國與國際外交",
      "platform": "x",
      "publishDate": "2026-04-29",
      "daysSincePublish": 30,
      "withinHarvestWindow": false,
      "harvestCount": 2,
      "lastHarvest": "2026-05-08"
    },
    {
      "n": 51,
      "article": "台灣邦交國與國際外交",
      "platform": "threads",
      "publishDate": "2026-04-29",
      "daysSincePublish": 30,
      "withinHarvestWindow": false,
      "harvestCount": 2,
      "lastHarvest": "2026-05-08"
    },
    {
      "n": 50,
      "article": "林琪兒",
      "platform": "x",
      "publishDate": "2026-04-28",
      "daysSincePublish": 31,
      "withinHarvestWindow": false,
      "harvestCount": 2,
      "lastHarvest": "2026-05-08"
    },
    {
      "n": 49,
      "article": "林琪兒",
      "platform": "threads",
      "publishDate": "2026-04-28",
      "daysSincePublish": 31,
      "withinHarvestWindow": false,
      "harvestCount": 2,
      "lastHarvest": "2026-05-08"
    },
    {
      "n": 48,
      "article": "沈伯洋",
      "platform": "x",
      "publishDate": "2026-04-28",
      "daysSincePublish": 31,
      "withinHarvestWindow": false,
      "harvestCount": 3,
      "lastHarvest": "2026-05-08"
    },
    {
      "n": 47,
      "article": "沈伯洋",
      "platform": "threads",
      "publishDate": "2026-04-28",
      "daysSincePublish": 31,
      "withinHarvestWindow": false,
      "harvestCount": 3,
      "lastHarvest": "2026-05-08"
    },
    {
      "n": 46,
      "article": "壞特",
      "platform": "x",
      "publishDate": "2026-04-26",
      "daysSincePublish": 33,
      "withinHarvestWindow": false,
      "harvestCount": 2,
      "lastHarvest": "2026-05-08"
    },
    {
      "n": 45,
      "article": "壞特",
      "platform": "threads",
      "publishDate": "2026-04-26",
      "daysSincePublish": 33,
      "withinHarvestWindow": false,
      "harvestCount": 2,
      "lastHarvest": "2026-05-08"
    },
    {
      "n": 44,
      "article": "田馥甄",
      "platform": "x",
      "publishDate": "2026-04-26",
      "daysSincePublish": 33,
      "withinHarvestWindow": false,
      "harvestCount": 2,
      "lastHarvest": "2026-05-08"
    },
    {
      "n": 43,
      "article": "田馥甄",
      "platform": "threads",
      "publishDate": "2026-04-26",
      "daysSincePublish": 33,
      "withinHarvestWindow": false,
      "harvestCount": 2,
      "lastHarvest": "2026-05-08"
    },
    {
      "n": 42,
      "article": "認知作戰",
      "platform": "x",
      "publishDate": "2026-04-23",
      "daysSincePublish": 36,
      "withinHarvestWindow": false,
      "harvestCount": 2,
      "lastHarvest": "2026-05-08"
    },
    {
      "n": 41,
      "article": "認知作戰",
      "platform": "threads",
      "publishDate": "2026-04-23",
      "daysSincePublish": 36,
      "withinHarvestWindow": false,
      "harvestCount": 2,
      "lastHarvest": "2026-05-08"
    },
    {
      "n": 40,
      "article": "謝德慶",
      "platform": "x",
      "publishDate": "2026-04-20",
      "daysSincePublish": 39,
      "withinHarvestWindow": false,
      "harvestCount": 1,
      "lastHarvest": "2026-05-08"
    },
    {
      "n": 39,
      "article": "謝德慶",
      "platform": "threads",
      "publishDate": "2026-04-20",
      "daysSincePublish": 39,
      "withinHarvestWindow": false,
      "harvestCount": 1,
      "lastHarvest": "2026-05-08"
    },
    {
      "n": 38,
      "article": "Portaly 首兩筆贊助感謝（站方 announcement）",
      "platform": "x",
      "publishDate": "2026-04-20",
      "daysSincePublish": 39,
      "withinHarvestWindow": false,
      "harvestCount": 1,
      "lastHarvest": "2026-05-08"
    },
    {
      "n": 37,
      "article": "Portaly 首兩筆贊助感謝（站方 announcement）",
      "platform": "threads",
      "publishDate": "2026-04-20",
      "daysSincePublish": 39,
      "withinHarvestWindow": false,
      "harvestCount": 1,
      "lastHarvest": "2026-05-08"
    },
    {
      "n": 36,
      "article": "台灣高鐵（v3 事實修正版）",
      "platform": "x",
      "publishDate": "2026-04-19",
      "daysSincePublish": 40,
      "withinHarvestWindow": false,
      "harvestCount": 1,
      "lastHarvest": "2026-05-08"
    },
    {
      "n": 35,
      "article": "台灣高鐵（v3 事實修正版）",
      "platform": "threads",
      "publishDate": "2026-04-19",
      "daysSincePublish": 40,
      "withinHarvestWindow": false,
      "harvestCount": 1,
      "lastHarvest": "2026-05-08"
    },
    {
      "n": 34,
      "article": "草東沒有派對（v2.1 首例）",
      "platform": "x",
      "publishDate": "2026-04-18",
      "daysSincePublish": 41,
      "withinHarvestWindow": false,
      "harvestCount": 1,
      "lastHarvest": "2026-05-08"
    },
    {
      "n": 33,
      "article": "草東沒有派對（v2.1 首例）",
      "platform": "threads",
      "publishDate": "2026-04-18",
      "daysSincePublish": 41,
      "withinHarvestWindow": false,
      "harvestCount": 2,
      "lastHarvest": "2026-05-08"
    },
    {
      "n": 32,
      "article": "Cicada（inline 連結實驗）",
      "platform": "x",
      "publishDate": "2026-04-18",
      "daysSincePublish": 41,
      "withinHarvestWindow": false,
      "harvestCount": 1,
      "lastHarvest": "2026-05-08"
    },
    {
      "n": 31,
      "article": "Cicada（inline 連結實驗）",
      "platform": "threads",
      "publishDate": "2026-04-18",
      "daysSincePublish": 41,
      "withinHarvestWindow": false,
      "harvestCount": 1,
      "lastHarvest": "2026-05-08"
    },
    {
      "n": 30,
      "article": "李洋（v3 場景修正）",
      "platform": "x",
      "publishDate": "2026-04-14",
      "daysSincePublish": 45,
      "withinHarvestWindow": false,
      "harvestCount": 1,
      "lastHarvest": "2026-05-08"
    },
    {
      "n": 29,
      "article": "🌋 李洋（v2，留言更正）",
      "platform": "threads",
      "publishDate": "2026-04-14",
      "daysSincePublish": 45,
      "withinHarvestWindow": false,
      "harvestCount": 1,
      "lastHarvest": "2026-05-08"
    },
    {
      "n": 28,
      "article": "李洋（⚠️ 已撤回）",
      "platform": "threads",
      "publishDate": "2026-04-14",
      "daysSincePublish": 45,
      "withinHarvestWindow": false,
      "harvestCount": 0,
      "lastHarvest": null
    },
    {
      "n": 27,
      "article": "張懸與安溥",
      "platform": "x",
      "publishDate": "2026-04-13",
      "daysSincePublish": 46,
      "withinHarvestWindow": false,
      "harvestCount": 1,
      "lastHarvest": "2026-05-08"
    },
    {
      "n": 26,
      "article": "韓國瑜",
      "platform": "x",
      "publishDate": "2026-04-13",
      "daysSincePublish": 46,
      "withinHarvestWindow": false,
      "harvestCount": 1,
      "lastHarvest": "2026-05-08"
    },
    {
      "n": 25,
      "article": "張懸與安溥",
      "platform": "threads",
      "publishDate": "2026-04-13",
      "daysSincePublish": 46,
      "withinHarvestWindow": false,
      "harvestCount": 1,
      "lastHarvest": "2026-05-08"
    },
    {
      "n": 24,
      "article": "韓國瑜",
      "platform": "threads",
      "publishDate": "2026-04-13",
      "daysSincePublish": 46,
      "withinHarvestWindow": false,
      "harvestCount": 1,
      "lastHarvest": "2026-05-08"
    },
    {
      "n": 23,
      "article": "鄭麗文",
      "platform": "x",
      "publishDate": "2026-04-11",
      "daysSincePublish": 48,
      "withinHarvestWindow": false,
      "harvestCount": 1,
      "lastHarvest": "2026-05-08"
    },
    {
      "n": 22,
      "article": "鄭麗文",
      "platform": "threads",
      "publishDate": "2026-04-11",
      "daysSincePublish": 48,
      "withinHarvestWindow": false,
      "harvestCount": 1,
      "lastHarvest": "2026-05-08"
    },
    {
      "n": 21,
      "article": "2026鄭習會與國共十年再會",
      "platform": "threads",
      "publishDate": "2026-04-11",
      "daysSincePublish": 48,
      "withinHarvestWindow": false,
      "harvestCount": 1,
      "lastHarvest": "2026-05-08"
    },
    {
      "n": 20,
      "article": "台灣動物用藥爭議",
      "platform": null,
      "publishDate": "2026-04-10",
      "daysSincePublish": 49,
      "withinHarvestWindow": false,
      "harvestCount": 0,
      "lastHarvest": null
    },
    {
      "n": 19,
      "article": "台灣動物用藥爭議",
      "platform": null,
      "publishDate": "2026-04-10",
      "daysSincePublish": 49,
      "withinHarvestWindow": false,
      "harvestCount": 0,
      "lastHarvest": null
    },
    {
      "n": 18,
      "article": "台灣國防與軍事現代化",
      "platform": null,
      "publishDate": "2026-04-10",
      "daysSincePublish": 49,
      "withinHarvestWindow": false,
      "harvestCount": 0,
      "lastHarvest": null
    },
    {
      "n": 17,
      "article": "台灣國防與軍事現代化",
      "platform": null,
      "publishDate": "2026-04-10",
      "daysSincePublish": 49,
      "withinHarvestWindow": false,
      "harvestCount": 0,
      "lastHarvest": null
    },
    {
      "n": 16,
      "article": "台灣感性",
      "platform": "x",
      "publishDate": "2026-04-08",
      "daysSincePublish": 51,
      "withinHarvestWindow": false,
      "harvestCount": 1,
      "lastHarvest": "2026-05-08"
    },
    {
      "n": 15,
      "article": "台灣感性",
      "platform": "threads",
      "publishDate": "2026-04-08",
      "daysSincePublish": 51,
      "withinHarvestWindow": false,
      "harvestCount": 2,
      "lastHarvest": "2026-05-08"
    },
    {
      "n": 14,
      "article": "台海危機與兩岸關係發展",
      "platform": "x",
      "publishDate": "2026-04-08",
      "daysSincePublish": 51,
      "withinHarvestWindow": false,
      "harvestCount": 1,
      "lastHarvest": "2026-05-08"
    },
    {
      "n": 13,
      "article": "台海危機與兩岸關係發展",
      "platform": "threads",
      "publishDate": "2026-04-08",
      "daysSincePublish": 51,
      "withinHarvestWindow": false,
      "harvestCount": 2,
      "lastHarvest": "2026-05-08"
    },
    {
      "n": 12,
      "article": "台灣民主轉型",
      "platform": "threads",
      "publishDate": "2026-04-07",
      "daysSincePublish": 52,
      "withinHarvestWindow": false,
      "harvestCount": 0,
      "lastHarvest": null
    },
    {
      "n": 11,
      "article": "台灣民主轉型",
      "platform": "x",
      "publishDate": "2026-04-07",
      "daysSincePublish": 52,
      "withinHarvestWindow": false,
      "harvestCount": 1,
      "lastHarvest": "2026-05-08"
    },
    {
      "n": 10,
      "article": "台灣民主轉型",
      "platform": "threads",
      "publishDate": "2026-04-07",
      "daysSincePublish": 52,
      "withinHarvestWindow": false,
      "harvestCount": 2,
      "lastHarvest": "2026-05-08"
    },
    {
      "n": 9,
      "article": "嚴長壽",
      "platform": "x",
      "publishDate": "2026-04-06",
      "daysSincePublish": 53,
      "withinHarvestWindow": false,
      "harvestCount": 1,
      "lastHarvest": "2026-05-08"
    },
    {
      "n": 8,
      "article": "嚴長壽",
      "platform": "threads",
      "publishDate": "2026-04-06",
      "daysSincePublish": 53,
      "withinHarvestWindow": false,
      "harvestCount": 2,
      "lastHarvest": "2026-05-08"
    },
    {
      "n": 7,
      "article": "台灣宗教與寺廟文化",
      "platform": "x",
      "publishDate": "2026-04-06",
      "daysSincePublish": 53,
      "withinHarvestWindow": false,
      "harvestCount": 1,
      "lastHarvest": "2026-05-08"
    },
    {
      "n": 6,
      "article": "台灣宗教與寺廟文化",
      "platform": "threads",
      "publishDate": "2026-04-06",
      "daysSincePublish": 53,
      "withinHarvestWindow": false,
      "harvestCount": 2,
      "lastHarvest": "2026-05-08"
    },
    {
      "n": 5,
      "article": "台灣國樂",
      "platform": "x",
      "publishDate": "2026-04-04",
      "daysSincePublish": 55,
      "withinHarvestWindow": false,
      "harvestCount": 1,
      "lastHarvest": "2026-05-08"
    },
    {
      "n": 4,
      "article": "台灣國樂",
      "platform": "threads",
      "publishDate": "2026-04-04",
      "daysSincePublish": 55,
      "withinHarvestWindow": false,
      "harvestCount": 2,
      "lastHarvest": "2026-05-08"
    },
    {
      "n": 3,
      "article": "林書豪",
      "platform": "threads",
      "publishDate": "2026-04-04",
      "daysSincePublish": 55,
      "withinHarvestWindow": false,
      "harvestCount": 0,
      "lastHarvest": null
    },
    {
      "n": 2,
      "article": "齊柏林",
      "platform": "threads",
      "publishDate": "2026-03-24",
      "daysSincePublish": 66,
      "withinHarvestWindow": false,
      "harvestCount": 0,
      "lastHarvest": null
    },
    {
      "n": 1,
      "article": "數位身分證與個資爭議",
      "platform": "threads",
      "publishDate": "2026-03-24",
      "daysSincePublish": 66,
      "withinHarvestWindow": false,
      "harvestCount": 0,
      "lastHarvest": null
    }
  ]
}
