{
  "total_zh": 3709,
  "total_en": 756,
  "coverage_en": 20.4,
  "categories": {
    "fr": {
      "zh": 755,
      "en": 0
    },
    "es": {
      "zh": 735,
      "en": 0
    },
    "History": {
      "zh": 41,
      "en": 42
    },
    "People": {
      "zh": 219,
      "en": 223
    },
    "ko": {
      "zh": 739,
      "en": 0
    },
    "Geography": {
      "zh": 49,
      "en": 47
    },
    "ja": {
      "zh": 744,
      "en": 0
    },
    "Food": {
      "zh": 53,
      "en": 56
    },
    "Technology": {
      "zh": 48,
      "en": 45
    },
    "Lifestyle": {
      "zh": 28,
      "en": 30
    },
    "About": {
      "zh": 6,
      "en": 6
    },
    "Society": {
      "zh": 73,
      "en": 74
    },
    "Culture": {
      "zh": 60,
      "en": 63
    },
    "Music": {
      "zh": 32,
      "en": 33
    },
    "Economy": {
      "zh": 53,
      "en": 56
    },
    "zh-TW": {
      "zh": 2,
      "en": 0
    },
    "Art": {
      "zh": 33,
      "en": 39
    },
    "Nature": {
      "zh": 37,
      "en": 38
    },
    "resources": {
      "zh": 2,
      "en": 2
    },
    "root": {
      "zh": 0,
      "en": 2
    }
  },
  "updated": "2026-05-20"
}